gb/__init__.py
gb/document.py
gb/entry.py
gb/magic.py
gb/mode.py
gb/protocol.py
gb/safe.py
gb-0.1.4.dist-info/LICENSE
gb-0.1.4.dist-info/METADATA
gb-0.1.4.dist-info/WHEEL
gb-0.1.4.dist-info/RECORD
