Metadata-Version: 2.1
Name: gb
Version: 0.1.4
Summary: A Python gopher library.
Home-page: https://github.com/gopherball/gb
License: MIT
Keywords: gopher,library
Author: Simon de Vlieger
Author-email: cmdr@supakeen.com
Requires-Python: >=3.9,<4
Classifier: License :: OSI Approved :: MIT License
Classifier: Programming Language :: Python
Classifier: Programming Language :: Python :: 3
Classifier: Programming Language :: Python :: 3.9
Classifier: Programming Language :: Python :: 3.10
Classifier: Programming Language :: Python :: 3.11
Classifier: Programming Language :: Python :: 3
Requires-Dist: python-magic (>=0.4.27,<0.5.0)
Project-URL: Repository, https://github.com/gopherball/gb
